pywt/__init__.py
pywt/_c99_config.py
pywt/_cwt.py
pywt/_doc_utils.py
pywt/_dwt.py
pywt/_functions.py
pywt/_mra.py
pywt/_multidim.py
pywt/_multilevel.py
pywt/_pytest.py
pywt/_pytesttester.py
pywt/_swt.py
pywt/_thresholding.py
pywt/_utils.py
pywt/_wavelet_packets.py
pywt/conftest.py
pywt/version.py
pywt/_extensions/__init__.py
pywt/_extensions/_cwt.cp39-win_amd64.pyd
pywt/_extensions/_dwt.cp39-win_amd64.pyd
pywt/_extensions/_pywt.cp39-win_amd64.pyd
pywt/_extensions/_swt.cp39-win_amd64.pyd
pywt/data/__init__.py
pywt/data/_readers.py
pywt/data/_wavelab_signals.py
pywt/data/aero.npz
pywt/data/ascent.npz
pywt/data/camera.npz
pywt/data/create_dat.py
pywt/data/ecg.npy
pywt/data/sst_nino3.npz
pywt/tests/test__pywt.py
pywt/tests/test_concurrent.py
pywt/tests/test_cwt_wavelets.py
pywt/tests/test_data.py
pywt/tests/test_deprecations.py
pywt/tests/test_doc.py
pywt/tests/test_dwt_idwt.py
pywt/tests/test_functions.py
pywt/tests/test_matlab_compatibility.py
pywt/tests/test_matlab_compatibility_cwt.py
pywt/tests/test_modes.py
pywt/tests/test_mra.py
pywt/tests/test_multidim.py
pywt/tests/test_multilevel.py
pywt/tests/test_perfect_reconstruction.py
pywt/tests/test_swt.py
pywt/tests/test_thresholding.py
pywt/tests/test_wavelet.py
pywt/tests/test_wp.py
pywt/tests/test_wp2d.py
pywt/tests/test_wpnd.py
pywt/tests/data/cwt_matlabR2015b_result.npz
pywt/tests/data/dwt_matlabR2012a_result.npz
pywt/tests/data/generate_matlab_data.py
pywt/tests/data/generate_matlab_data_cwt.py
pywt/tests/data/wavelab_test_signals.npz
PyWavelets-1.4.0.dist-info/LICENSE
PyWavelets-1.4.0.dist-info/LICENSES_bundled.txt
PyWavelets-1.4.0.dist-info/METADATA
PyWavelets-1.4.0.dist-info/WHEEL
PyWavelets-1.4.0.dist-info/top_level.txt
PyWavelets-1.4.0.dist-info/RECORD
