Metadata-Version: 2.1
Name: PyWavelets
Version: 1.4.0
Summary: PyWavelets, wavelet transform module
Home-page: https://github.com/PyWavelets/pywt
Maintainer: The PyWavelets Developers
Maintainer-email: pywavelets@googlegroups.com
License: MIT
Download-URL: https://github.com/PyWavelets/pywt/releases
Keywords: wavelets,wavelet transform,DWT,SWT,CWT,scientific
Platform: Windows
Platform: Linux
Platform: Solaris
Platform: Mac OS-X
Platform: Unix
Classifier: Development Status :: 5 - Production/Stable
Classifier: Intended Audience :: Developers
Classifier: Intended Audience :: Education
Classifier: Intended Audience :: Science/Research
Classifier: License :: OSI Approved :: MIT License
Classifier: Operating System :: OS Independent
Classifier: Programming Language :: C
Classifier: Programming Language :: Python
Classifier: Programming Language :: Python :: 3
Classifier: Programming Language :: Python :: 3.7
Classifier: Programming Language :: Python :: 3.8
Classifier: Programming Language :: Python :: 3.9
Classifier: Programming Language :: Python :: 3.10
Classifier: Topic :: Software Development :: Libraries :: Python Modules
Requires-Python: >=3.7
License-File: LICENSE
License-File: LICENSES_bundled.txt
